shotgun_api3/__init__.py
shotgun_api3/shotgun.py
shotgun_api3/lib/__init__.py
shotgun_api3/lib/pyparsing.py
shotgun_api3/lib/sgtimezone.py
shotgun_api3/lib/certifi/__init__.py
shotgun_api3/lib/certifi/__main__.py
shotgun_api3/lib/certifi/cacert.pem
shotgun_api3/lib/certifi/core.py
shotgun_api3/lib/certifi/py.typed
shotgun_api3/lib/httplib2/__init__.py
shotgun_api3/lib/httplib2/auth.py
shotgun_api3/lib/httplib2/cacerts.txt
shotgun_api3/lib/httplib2/certs.py
shotgun_api3/lib/httplib2/error.py
shotgun_api3/lib/httplib2/iri2uri.py
shotgun_api3/lib/httplib2/socks.py
shotgun_api3/lib/mockgun/__init__.py
shotgun_api3/lib/mockgun/errors.py
shotgun_api3/lib/mockgun/mockgun.py
shotgun_api3/lib/mockgun/schema.py
shotgun_api3-3.9.0.dist-info/licenses/LICENSE
shotgun_api3-3.9.0.dist-info/METADATA
shotgun_api3-3.9.0.dist-info/WHEEL
shotgun_api3-3.9.0.dist-info/top_level.txt
shotgun_api3-3.9.0.dist-info/RECORD
